{
  "name": "roq/Statistics",
  "type": "item",
  "comment": "Represents a single statistic",
  "values": [
    {
      "name": "type",
      "type": "roq/StatisticsType",
      "comment": "Statistics type"
    },
    {
      "name": "value",
      "type": "std/double",
      "comment": "Value"
    },
    {
      "name": "beginTimeUtc",
      "type": "std/seconds",
      "comment": "Sample period begin time"
    },
    {
      "name": "endTimeUtc",
      "type": "std/seconds",
      "comment": "Sample period end time"
    }
  ]
}
